{"ProjectWatches":"{\"Value\":[]}","OpenedDocuments":"[\"Main.xaml\"]","ProjectBreakpoints":"{\"Value\":{}}","ProjectActivitiesViewState":"{\"Main.xaml\":[{\"ActivityIdRef\":\"WriteLine_1\",\"IsAdvancedOptionsExpanded\":false,\"Widgets\":{}},{\"ActivityIdRef\":\"AppendItemToCollection`1_1\",\"IsAdvancedOptionsExpanded\":true,\"Categories\":{\"출력\":true},\"Widgets\":{}},{\"ActivityIdRef\":\"WriteLine_2\",\"IsAdvancedOptionsExpanded\":false,\"Widgets\":{}},{\"ActivityIdRef\":\"WriteLine_3\",\"IsAdvancedOptionsExpanded\":false,\"Widgets\":{}}]}"}